LICENSE
README.rst
pyproject.toml
setup.cfg
setup.py
http_noah/__init__.py
http_noah/async_client.py
http_noah/common.py
http_noah/sync_client.py
http_noah/utils.py
http_noah.egg-info/PKG-INFO
http_noah.egg-info/SOURCES.txt
http_noah.egg-info/dependency_links.txt
http_noah.egg-info/requires.txt
http_noah.egg-info/top_level.txt
tests/__init__.py
tests/async_tests.py
tests/common.py
tests/models.py
tests/server.py
tests/sync_tests.py