Metadata-Version: 2.1
Name: http-noah
Version: 0.1.10
Summary: REST-minded yet generic HTTP Python client with both async and sync interfaces
Home-page: https://github.com/haizaar/http-noah
Author: Zaar Hai
Author-email: haizaar@haizaar.com
License:                                  Apache License
